Wrapper_Weather_Module/__init__.py
Wrapper_Weather_Module/functions/__init__.py
Wrapper_Weather_Module/functions/functions.py
Wrapper_Weather_Module/main/__init__.py
Wrapper_Weather_Module/main/main.py
Wrapper_Weather_Module-0.0.1.dist-info/METADATA
Wrapper_Weather_Module-0.0.1.dist-info/WHEEL
Wrapper_Weather_Module-0.0.1.dist-info/top_level.txt
Wrapper_Weather_Module-0.0.1.dist-info/RECORD
